termpandas/__init__.py
termpandas/scrollable.py
termpandas-0.2.3.dist-info/LICENSE
termpandas-0.2.3.dist-info/METADATA
termpandas-0.2.3.dist-info/WHEEL
termpandas-0.2.3.dist-info/top_level.txt
termpandas-0.2.3.dist-info/RECORD
