Metadata-Version: 2.1
Name: termpandas
Version: 0.2.3
Summary: Scrollable pandas dataframes in the terminal.
Home-page: https://github.com/juan-esteban-berger/termpandas
Author: Juan Esteban Berger
Author-email: juanestebanberger@gmail.com
Project-URL: Source Code, https://github.com/juan-esteban-berger/termpandas
Classifier: Development Status :: 3 - Alpha
Classifier: Intended Audience :: Developers
Classifier: Topic :: Software Development :: Libraries :: Python Modules
Classifier: License :: OSI Approved :: MIT License
Classifier: Programming Language :: Python :: 3
Classifier: Programming Language :: Python :: 3.10
Classifier: Operating System :: OS Independent
License-File: LICENSE
Requires-Dist: pandas >=2.1.4
Requires-Dist: blessings >=1.7
Requires-Dist: curtsies >=0.4.2
Requires-Dist: polars >=0.18.0
